setup.py
Checkerproxy/__init__.py
Checkerproxy.egg-info/PKG-INFO
Checkerproxy.egg-info/SOURCES.txt
Checkerproxy.egg-info/dependency_links.txt
Checkerproxy.egg-info/not-zip-safe
Checkerproxy.egg-info/requires.txt
Checkerproxy.egg-info/top_level.txt