Metadata-Version: 1.0
Name: Checkerproxy
Version: 0.2
Summary: Get active proxies from checkerproxy.net
Home-page: https://github.com/MorrisCasper/Checkerproxy
Author: MorrisCasper
Author-email: UNKNOWN
License: MIT
Platform: UNKNOWN
